checks/__init__.py
checks/complexity.py
checks/deprecated_functions.py
checks/docstrings.py
checks/indentation.py
checks/magic_methods.py
checks/magic_numbers.py
checks/naming_conventions.py
checks/type_hints.py
checks/unused_imports.py
utils/__init__.py
utils/ast_utils.py
utils/formatting.py
splint-0.1.dist-info/LICENSE
splint-0.1.dist-info/METADATA
splint-0.1.dist-info/WHEEL
splint-0.1.dist-info/top_level.txt
splint-0.1.dist-info/RECORD
