Metadata-Version: 2.1
Name: splint
Version: 0.1
Summary: Splint: A simple, easy-to-use Python linter designed for beginner developers.
Home-page: https://github.com/jerankda/splint
Author: Daniel Jeranko
Author-email: danieljeranko@skittle.cc
License: UNKNOWN
Platform: UNKNOWN
Classifier: Programming Language :: Python :: 3
Classifier: License :: OSI Approved :: MIT License
Classifier: Operating System :: OS Independent
Classifier: Development Status :: 3 - Alpha
Classifier: Intended Audience :: Developers
Classifier: Topic :: Software Development :: Quality Assurance
Classifier: Programming Language :: Python :: 3 :: Only
Requires-Python: >=3.6
License-File: LICENSE
